Compiled from "Server.kt"
public final class core.Server {
  public static final core.Server INSTANCE;

  public static long startTime;

  private static long lastHeartbeat;

  private static boolean running;

  private static core.net.NioReactor reactor;

  private static core.tools.NetworkReachability networkReachability;

  private core.Server();
    Code:
         0: aload_0
         1: invokespecial #8                  // Method java/lang/Object."<init>":()V
         4: return

  public final long getLastHeartbeat();
    Code:
         0: getstatic     #16                 // Field lastHeartbeat:J
         3: lreturn

  public final void setLastHeartbeat(long);
    Code:
         0: lload_1
         1: putstatic     #16                 // Field lastHeartbeat:J
         4: return

  public static final boolean getRunning();
    Code:
         0: getstatic     #25                 // Field running:Z
         3: ireturn

  public static final void setRunning(boolean);
    Code:
         0: iload_0
         1: putstatic     #25                 // Field running:Z
         4: return

  public static void getRunning$annotations();
    Code:
         0: return

  public static final core.net.NioReactor getReactor();
    Code:
         0: getstatic     #36                 // Field reactor:Lcore/net/NioReactor;
         3: areturn

  public static final void setReactor(core.net.NioReactor);
    Code:
         0: aload_0
         1: putstatic     #36                 // Field reactor:Lcore/net/NioReactor;
         4: return

  public static void getReactor$annotations();
    Code:
         0: return

  public final core.tools.NetworkReachability getNetworkReachability();
    Code:
         0: getstatic     #46                 // Field networkReachability:Lcore/tools/NetworkReachability;
         3: areturn

  public final void setNetworkReachability(core.tools.NetworkReachability);
    Code:
         0: aload_1
         1: ldc           #49                 // String <set-?>
         3: invokestatic  #55                 // Method kotlin/jvm/internal/Intrinsics.checkNotNullParameter:(Ljava/lang/Object;Ljava/lang/String;)V
         6: aload_1
         7: putstatic     #46                 // Field networkReachability:Lcore/tools/NetworkReachability;
        10: return

  public static final void main(java.lang.String[]) throws java.lang.Throwable;
    Code:
         0: aload_0
         1: ldc           #63                 // String args
         3: invokestatic  #55                 // Method kotlin/jvm/internal/Intrinsics.checkNotNullParameter:(Ljava/lang/Object;Ljava/lang/String;)V
         6: aload_0
         7: arraylength
         8: ifne          15
        11: iconst_1
        12: goto          16
        15: iconst_0
        16: ifne          23
        19: iconst_1
        20: goto          24
        23: iconst_0
        24: ifeq          59
        27: getstatic     #66                 // Field INSTANCE:Lcore/Server;
        30: invokevirtual #70                 // Method java/lang/Object.getClass:()Ljava/lang/Class;
        33: getstatic     #76                 // Field core/tools/Log.INFO:Lcore/tools/Log;
        36: aload_0
        37: iconst_0
        38: aaload
        39: invokedynamic #88,  0             // InvokeDynamic #0:makeConcatWithConstants:(Ljava/lang/String;)Ljava/lang/String;
        44: invokestatic  #94                 // Method core/api/ContentAPIKt.log:(Ljava/lang/Class;Lcore/tools/Log;Ljava/lang/String;)V
        47: getstatic     #99                 // Field core/game/system/config/ServerConfigParser.INSTANCE:Lcore/game/system/config/ServerConfigParser;
        50: aload_0
        51: iconst_0
        52: aaload
        53: invokevirtual #103                // Method core/game/system/config/ServerConfigParser.parse:(Ljava/lang/String;)V
        56: goto          93
        59: getstatic     #66                 // Field INSTANCE:Lcore/Server;
        62: invokevirtual #70                 // Method java/lang/Object.getClass:()Ljava/lang/Class;
        65: getstatic     #76                 // Field core/tools/Log.INFO:Lcore/tools/Log;
        68: getstatic     #109                // Field java/io/File.separator:Ljava/lang/String;
        71: invokedynamic #112,  0            // InvokeDynamic #1:makeConcatWithConstants:(Ljava/lang/String;)Ljava/lang/String;
        76: invokestatic  #94                 // Method core/api/ContentAPIKt.log:(Ljava/lang/Class;Lcore/tools/Log;Ljava/lang/String;)V
        79: getstatic     #99                 // Field core/game/system/config/ServerConfigParser.INSTANCE:Lcore/game/system/config/ServerConfigParser;
        82: getstatic     #109                // Field java/io/File.separator:Ljava/lang/String;
        85: invokedynamic #115,  0            // InvokeDynamic #2:makeConcatWithConstants:(Ljava/lang/String;)Ljava/lang/String;
        90: invokevirtual #103                // Method core/game/system/config/ServerConfigParser.parse:(Ljava/lang/String;)V
        93: getstatic     #66                 // Field INSTANCE:Lcore/Server;
        96: pop
        97: invokestatic  #120                // Method java/lang/System.currentTimeMillis:()J
       100: putstatic     #123                // Field startTime:J
       103: new           #125                // class core/tools/TimeStamp
       106: dup
       107: invokespecial #126                // Method core/tools/TimeStamp."<init>":()V
       110: astore_1
       111: iconst_1
       112: invokestatic  #131                // Method core/game/world/GameWorld.prompt:(Z)V
       115: invokestatic  #137                // Method java/lang/Runtime.getRuntime:()Ljava/lang/Runtime;
       118: getstatic     #143                // Field core/ServerConstants.SHUTDOWN_HOOK:Ljava/lang/Thread;
       121: invokevirtual #147                // Method java/lang/Runtime.addShutdownHook:(Ljava/lang/Thread;)V
       124: getstatic     #66                 // Field INSTANCE:Lcore/Server;
       127: invokevirtual #70                 // Method java/lang/Object.getClass:()Ljava/lang/Class;
       130: getstatic     #76                 // Field core/tools/Log.INFO:Lcore/tools/Log;
       133: ldc           #149                // String Starting networking...
       135: invokestatic  #94                 // Method core/api/ContentAPIKt.log:(Ljava/lang/Class;Lcore/tools/Log;Ljava/lang/String;)V
       138: nop
       139: getstatic     #66                 // Field INSTANCE:Lcore/Server;
       142: pop
       143: ldc           #150                // int 43594
       145: invokestatic  #154                // Method core/game/world/GameWorld.getSettings:()Lcore/game/world/GameSettings;
       148: dup
       149: ifnull        161
       152: invokevirtual #160                // Method core/game/world/GameSettings.getWorldId:()I
       155: invokestatic  #166                // Method java/lang/Integer.valueOf:(I)Ljava/lang/Integer;
       158: goto          163
       161: pop
       162: aconst_null
       163: dup
       164: invokestatic  #170                // Method kotlin/jvm/internal/Intrinsics.checkNotNull:(Ljava/lang/Object;)V
       167: invokevirtual #173                // Method java/lang/Integer.intValue:()I
       170: iadd
       171: invokestatic  #179                // Method core/net/NioReactor.configure:(I)Lcore/net/NioReactor;
       174: putstatic     #36                 // Field reactor:Lcore/net/NioReactor;
       177: getstatic     #66                 // Field INSTANCE:Lcore/Server;
       180: pop
       181: getstatic     #36                 // Field reactor:Lcore/net/NioReactor;
       184: dup
       185: invokestatic  #170                // Method kotlin/jvm/internal/Intrinsics.checkNotNull:(Ljava/lang/Object;)V
       188: invokevirtual #182                // Method core/net/NioReactor.start:()V
       191: goto          242
       194: astore_2
       195: getstatic     #66                 // Field INSTANCE:Lcore/Server;
       198: invokevirtual #70                 // Method java/lang/Object.getClass:()Ljava/lang/Class;
       201: getstatic     #185                // Field core/tools/Log.ERR:Lcore/tools/Log;
       204: ldc           #150                // int 43594
       206: invokestatic  #154                // Method core/game/world/GameWorld.getSettings:()Lcore/game/world/GameSettings;
       209: dup
       210: ifnull        222
       213: invokevirtual #160                // Method core/game/world/GameSettings.getWorldId:()I
       216: invokestatic  #166                // Method java/lang/Integer.valueOf:(I)Ljava/lang/Integer;
       219: goto          224
       222: pop
       223: aconst_null
       224: dup
       225: invokestatic  #170                // Method kotlin/jvm/internal/Intrinsics.checkNotNull:(Ljava/lang/Object;)V
       228: invokevirtual #173                // Method java/lang/Integer.intValue:()I
       231: iadd
       232: invokedynamic #190,  0            // InvokeDynamic #3:makeConcatWithConstants:(I)Ljava/lang/String;
       237: invokestatic  #94                 // Method core/api/ContentAPIKt.log:(Ljava/lang/Class;Lcore/tools/Log;Ljava/lang/String;)V
       240: aload_2
       241: athrow
       242: getstatic     #66                 // Field INSTANCE:Lcore/Server;
       245: invokevirtual #70                 // Method java/lang/Object.getClass:()Ljava/lang/Class;
       248: getstatic     #76                 // Field core/tools/Log.INFO:Lcore/tools/Log;
       251: invokestatic  #154                // Method core/game/world/GameWorld.getSettings:()Lcore/game/world/GameSettings;
       254: dup
       255: ifnull        264
       258: invokevirtual #194                // Method core/game/world/GameSettings.getName:()Ljava/lang/String;
       261: goto          266
       264: pop
       265: aconst_null
       266: invokestatic  #154                // Method core/game/world/GameWorld.getSettings:()Lcore/game/world/GameSettings;
       269: dup
       270: ifnull        279
       273: invokevirtual #197                // Method core/game/world/GameSettings.toString:()Ljava/lang/String;
       276: goto          281
       279: pop
       280: aconst_null
       281: invokedynamic #202,  0            // InvokeDynamic #4:makeConcatWithConstants:(Ljava/lang/String;Ljava/lang/String;)Ljava/lang/String;
       286: invokestatic  #94                 // Method core/api/ContentAPIKt.log:(Ljava/lang/Class;Lcore/tools/Log;Ljava/lang/String;)V
       289: getstatic     #66                 // Field INSTANCE:Lcore/Server;
       292: invokevirtual #70                 // Method java/lang/Object.getClass:()Ljava/lang/Class;
       295: getstatic     #76                 // Field core/tools/Log.INFO:Lcore/tools/Log;
       298: invokestatic  #154                // Method core/game/world/GameWorld.getSettings:()Lcore/game/world/GameSettings;
       301: dup
       302: ifnull        311
       305: invokevirtual #194                // Method core/game/world/GameSettings.getName:()Ljava/lang/String;
       308: goto          313
       311: pop
       312: aconst_null
       313: aload_1
       314: iconst_0
       315: ldc           #204                // String
       317: invokevirtual #208                // Method core/tools/TimeStamp.duration:(ZLjava/lang/String;)J
       320: invokedynamic #213,  0            // InvokeDynamic #5:makeConcatWithConstants:(Ljava/lang/String;J)Ljava/lang/String;
       325: invokestatic  #94                 // Method core/api/ContentAPIKt.log:(Ljava/lang/Class;Lcore/tools/Log;Ljava/lang/String;)V
       328: new           #215                // class java/util/Scanner
       331: dup
       332: getstatic     #219                // Field java/lang/System.in:Ljava/io/InputStream;
       335: invokespecial #222                // Method java/util/Scanner."<init>":(Ljava/io/InputStream;)V
       338: astore_2
       339: getstatic     #66                 // Field INSTANCE:Lcore/Server;
       342: pop
       343: iconst_1
       344: putstatic     #25                 // Field running:Z
       347: getstatic     #227                // Field kotlinx/coroutines/GlobalScope.INSTANCE:Lkotlinx/coroutines/GlobalScope;
       350: checkcast     #229                // class kotlinx/coroutines/CoroutineScope
       353: aconst_null
       354: aconst_null
       355: new           #231                // class core/Server$main$1
       358: dup
       359: aload_2
       360: aconst_null
       361: invokespecial #234                // Method core/Server$main$1."<init>":(Ljava/util/Scanner;Lkotlin/coroutines/Continuation;)V
       364: checkcast     #236                // class kotlin/jvm/functions/Function2
       367: iconst_3
       368: aconst_null
       369: invokestatic  #242                // Method kotlinx/coroutines/BuildersKt.launch$default:(Lkotlinx/coroutines/CoroutineScope;Lkotlin/coroutines/CoroutineContext;Lkotlinx/coroutines/CoroutineStart;Lkotlin/jvm/functions/Function2;ILjava/lang/Object;)Lkotlinx/coroutines/Job;
       372: pop
       373: getstatic     #245                // Field core/ServerConstants.WATCHDOG_ENABLED:Z
       376: ifeq          404
       379: getstatic     #227                // Field kotlinx/coroutines/GlobalScope.INSTANCE:Lkotlinx/coroutines/GlobalScope;
       382: checkcast     #229                // class kotlinx/coroutines/CoroutineScope
       385: aconst_null
       386: aconst_null
       387: new           #247                // class core/Server$main$2
       390: dup
       391: aconst_null
       392: invokespecial #250                // Method core/Server$main$2."<init>":(Lkotlin/coroutines/Continuation;)V
       395: checkcast     #236                // class kotlin/jvm/functions/Function2
       398: iconst_3
       399: aconst_null
       400: invokestatic  #242                // Method kotlinx/coroutines/BuildersKt.launch$default:(Lkotlinx/coroutines/CoroutineScope;Lkotlin/coroutines/CoroutineContext;Lkotlinx/coroutines/CoroutineStart;Lkotlin/jvm/functions/Function2;ILjava/lang/Object;)Lkotlinx/coroutines/Job;
       403: pop
       404: return
      Exception table:
         from    to  target type
           138   191   194   Class java/net/BindException

  private final boolean checkConnectivity();
    Code:
         0: getstatic     #268                // Field core/ServerConstants.CONNECTIVITY_CHECK_URL:Ljava/lang/String;
         3: checkcast     #270                // class java/lang/CharSequence
         6: iconst_1
         7: anewarray     #262                // class java/lang/String
        10: astore_2
        11: aload_2
        12: iconst_0
        13: ldc_w         #272                // String ,
        16: aastore
        17: aload_2
        18: iconst_0
        19: iconst_0
        20: bipush        6
        22: aconst_null
        23: invokestatic  #278                // Method kotlin/text/StringsKt.split$default:(Ljava/lang/CharSequence;[Ljava/lang/String;ZIILjava/lang/Object;)Ljava/util/List;
        26: astore_1
        27: getstatic     #282                // Field core/ServerConstants.CONNECTIVITY_TIMEOUT:I
        30: istore_2
        31: iload_2
        32: aload_1
        33: invokeinterface #287,  1          // InterfaceMethod java/util/List.size:()I
        38: imul
        39: sipush        5000
        42: if_icmple     56
        45: sipush        5000
        48: aload_1
        49: invokeinterface #287,  1          // InterfaceMethod java/util/List.size:()I
        54: idiv
        55: istore_2
        56: aload_1
        57: invokeinterface #291,  1          // InterfaceMethod java/util/List.iterator:()Ljava/util/Iterator;
        62: astore_3
        63: aload_3
        64: invokeinterface #296,  1          // InterfaceMethod java/util/Iterator.hasNext:()Z
        69: ifeq          145
        72: aload_3
        73: invokeinterface #300,  1          // InterfaceMethod java/util/Iterator.next:()Ljava/lang/Object;
        78: checkcast     #262                // class java/lang/String
        81: astore        4
        83: nop
        84: new           #302                // class java/net/URL
        87: dup
        88: aload         4
        90: invokespecial #304                // Method java/net/URL."<init>":(Ljava/lang/String;)V
        93: astore        5
        95: aload         5
        97: invokevirtual #308                // Method java/net/URL.openConnection:()Ljava/net/URLConnection;
       100: astore        6
       102: aload         6
       104: iload_2
       105: invokevirtual #314                // Method java/net/URLConnection.setConnectTimeout:(I)V
       108: aload         6
       110: invokevirtual #317                // Method java/net/URLConnection.connect:()V
       113: aload         6
       115: invokevirtual #321                // Method java/net/URLConnection.getInputStream:()Ljava/io/InputStream;
       118: invokevirtual #326                // Method java/io/InputStream.close:()V
       121: iconst_1
       122: ireturn
       123: astore        5
       125: aload_0
       126: invokevirtual #70                 // Method java/lang/Object.getClass:()Ljava/lang/Class;
       129: getstatic     #329                // Field core/tools/Log.WARN:Lcore/tools/Log;
       132: aload         4
       134: invokedynamic #332,  0            // InvokeDynamic #6:makeConcatWithConstants:(Ljava/lang/String;)Ljava/lang/String;
       139: invokestatic  #94                 // Method core/api/ContentAPIKt.log:(Ljava/lang/Class;Lcore/tools/Log;Ljava/lang/String;)V
       142: goto          63
       145: iconst_0
       146: ireturn
      Exception table:
         from    to  target type
            83   123   123   Class java/lang/Exception

  public static final void heartbeat();
    Code:
         0: getstatic     #66                 // Field INSTANCE:Lcore/Server;
         3: pop
         4: invokestatic  #120                // Method java/lang/System.currentTimeMillis:()J
         7: putstatic     #16                 // Field lastHeartbeat:J
        10: return

  public final void printCommands();
    Code:
         0: ldc_w         #345                // String stop - stop the server (saves all accounts and such)
         3: getstatic     #349                // Field java/lang/System.out:Ljava/io/PrintStream;
         6: swap
         7: invokevirtual #354                // Method java/io/PrintStream.println:(Ljava/lang/Object;)V
        10: ldc_w         #356                // String players - show online player count
        13: getstatic     #349                // Field java/lang/System.out:Ljava/io/PrintStream;
        16: swap
        17: invokevirtual #354                // Method java/io/PrintStream.println:(Ljava/lang/Object;)V
        20: ldc_w         #358                // String update - initiate an update with a countdown visible to players
        23: getstatic     #349                // Field java/lang/System.out:Ljava/io/PrintStream;
        26: swap
        27: invokevirtual #354                // Method java/io/PrintStream.println:(Ljava/lang/Object;)V
        30: ldc_w         #360                // String help, commands - show this
        33: getstatic     #349                // Field java/lang/System.out:Ljava/io/PrintStream;
        36: swap
        37: invokevirtual #354                // Method java/io/PrintStream.println:(Ljava/lang/Object;)V
        40: ldc_w         #362                // String restartworker - Reboots the major update worker in case of a travesty.
        43: getstatic     #349                // Field java/lang/System.out:Ljava/io/PrintStream;
        46: swap
        47: invokevirtual #354                // Method java/io/PrintStream.println:(Ljava/lang/Object;)V
        50: return

  public final void autoReconnect();
    Code:
         0: return

  public final long getStartTime();
    Code:
         0: getstatic     #123                // Field startTime:J
         3: lreturn

  private final java.lang.String threadDump(boolean, boolean);
    Code:
         0: new           #368                // class java/lang/StringBuffer
         3: dup
         4: invokestatic  #371                // Method java/lang/System.lineSeparator:()Ljava/lang/String;
         7: invokespecial #372                // Method java/lang/StringBuffer."<init>":(Ljava/lang/String;)V
        10: astore_3
        11: invokestatic  #378                // Method java/lang/management/ManagementFactory.getThreadMXBean:()Ljava/lang/management/ThreadMXBean;
        14: dup
        15: ldc_w         #380                // String getThreadMXBean()
        18: invokestatic  #383                // Method kotlin/jvm/internal/Intrinsics.checkNotNullExpressionValue:(Ljava/lang/Object;Ljava/lang/String;)V
        21: astore        4
        23: aload         4
        25: iload_1
        26: iload_2
        27: invokeinterface #389,  3          // InterfaceMethod java/lang/management/ThreadMXBean.dumpAllThreads:(ZZ)[Ljava/lang/management/ThreadInfo;
        32: dup
        33: ldc_w         #391                // String threadMXBean.dumpAllThre?ors, lockedSynchronizers)
        36: invokestatic  #383                // Method kotlin/jvm/internal/Intrinsics.checkNotNullExpressionValue:(Ljava/lang/Object;Ljava/lang/String;)V
        39: astore        5
        41: iconst_0
        42: istore        6
        44: aload         5
        46: arraylength
        47: istore        7
        49: iload         6
        51: iload         7
        53: if_icmpge     79
        56: aload         5
        58: iload         6
        60: aaload
        61: astore        8
        63: aload_3
        64: aload         8
        66: invokevirtual #394                // Method java/lang/management/ThreadInfo.toString:()Ljava/lang/String;
        69: invokevirtual #398                // Method java/lang/StringBuffer.append:(Ljava/lang/String;)Ljava/lang/StringBuffer;
        72: pop
        73: iinc          6, 1
        76: goto          49
        79: aload_3
        80: invokevirtual #399                // Method java/lang/StringBuffer.toString:()Ljava/lang/String;
        83: areturn

  public final void setStartTime(long);
    Code:
         0: getstatic     #66                 // Field INSTANCE:Lcore/Server;
         3: pop
         4: lload_1
         5: putstatic     #123                // Field startTime:J
         8: return

  public static final boolean access$checkConnectivity(core.Server);
    Code:
         0: aload_0
         1: invokespecial #413                // Method checkConnectivity:()Z
         4: ireturn

  public static final java.lang.String access$threadDump(core.Server, boolean, boolean);
    Code:
         0: aload_0
         1: iload_1
         2: iload_2
         3: invokespecial #418                // Method threadDump:(ZZ)Ljava/lang/String;
         6: areturn

  static {};
    Code:
         0: new           #2                  // class core/Server
         3: dup
         4: invokespecial #420                // Method "<init>":()V
         7: putstatic     #66                 // Field INSTANCE:Lcore/Server;
        10: invokestatic  #120                // Method java/lang/System.currentTimeMillis:()J
        13: putstatic     #16                 // Field lastHeartbeat:J
        16: getstatic     #425                // Field core/tools/NetworkReachability.Reachable:Lcore/tools/NetworkReachability;
        19: putstatic     #46                 // Field networkReachability:Lcore/tools/NetworkReachability;
        22: return
}
